edgar_sec_mcp/__init__.py
edgar_sec_mcp/server.py
edgar_sec_mcp/util.py
edgar_sec_mcp/edgar/__init__.py
edgar_sec_mcp/edgar/filings.py
edgar_sec_mcp/edgar/models.py
edgar_sec_mcp/edgar/sec_forms.py
edgar_sec_mcp/edgar/util.py
iflow_mcp_flothjl_edgar_sec_mcp-0.1.0.dist-info/METADATA
iflow_mcp_flothjl_edgar_sec_mcp-0.1.0.dist-info/WHEEL
iflow_mcp_flothjl_edgar_sec_mcp-0.1.0.dist-info/entry_points.txt
iflow_mcp_flothjl_edgar_sec_mcp-0.1.0.dist-info/RECORD
