Metadata-Version: 2.4
Name: iflow-mcp_flothjl_edgar-sec-mcp
Version: 0.1.0
Summary: Add your description here
Author-email: Josh Floth <flothjldev@proton.me>
Requires-Python: >=3.13
Requires-Dist: beautifulsoup4>=4.13.3
Requires-Dist: httpx>=0.28.1
Requires-Dist: ixbrlparse>=0.10.0
Requires-Dist: mcp[cli]>=1.3.0
